hybridcryptosystem/__init__.py
hybridcryptosystem/hybridcryptosystem.py
hybridcryptosystem-0.0.0.dist-info/LICENSE
hybridcryptosystem-0.0.0.dist-info/METADATA
hybridcryptosystem-0.0.0.dist-info/WHEEL
hybridcryptosystem-0.0.0.dist-info/top_level.txt
hybridcryptosystem-0.0.0.dist-info/RECORD
