Metadata-Version: 2.1
Name: hybridcryptosystem
Version: 0.0.0
Summary: Coming soon
Author-email: Sira Pornsiriprasert <code@psira.me>
Classifier: Programming Language :: Python :: 3
Classifier: License :: OSI Approved :: BSD License
Classifier: Operating System :: OS Independent
Requires-Python: >=3.8
License-File: LICENSE
Requires-Dist: cryptography
